pyshacl/__init__.py
pyshacl/__main__.py
pyshacl/assets/dash.pickle
pyshacl/assets/dash.ttl
pyshacl/assets/make_builtin.py
pyshacl/assets/schema.pickle
pyshacl/assets/schema.ttl
pyshacl/assets/shacl-shacl.pickle
pyshacl/assets/shacl-shacl.ttl
pyshacl/assets/shacl.pickle
pyshacl/assets/shacl.ttl
pyshacl/cli.py
pyshacl/cli_rules.py
pyshacl/constraints/__init__.py
pyshacl/constraints/advanced/__init__.py
pyshacl/constraints/constraint_component.py
pyshacl/constraints/core/__init__.py
pyshacl/constraints/core/cardinality_constraints.py
pyshacl/constraints/core/logical_constraints.py
pyshacl/constraints/core/other_constraints.py
pyshacl/constraints/core/property_pair_constraints.py
pyshacl/constraints/core/shape_based_constraints.py
pyshacl/constraints/core/string_based_constraints.py
pyshacl/constraints/core/value_constraints.py
pyshacl/constraints/core/value_range_constraints.py
pyshacl/constraints/sparql/__init__.py
pyshacl/constraints/sparql/sparql_based_constraint_components.py
pyshacl/constraints/sparql/sparql_based_constraints.py
pyshacl/consts.py
pyshacl/entrypoints.py
pyshacl/errors.py
pyshacl/extras/__init__.py
pyshacl/extras/js/__init__.py
pyshacl/extras/js/constraint.py
pyshacl/extras/js/constraint_component.py
pyshacl/extras/js/context.py
pyshacl/extras/js/function.py
pyshacl/extras/js/js_executable.py
pyshacl/extras/js/loader.py
pyshacl/extras/js/rules.py
pyshacl/extras/js/target.py
pyshacl/functions/__init__.py
pyshacl/functions/shacl_function.py
pyshacl/helper/__init__.py
pyshacl/helper/expression_helper.py
pyshacl/helper/path_helper.py
pyshacl/helper/sparql_query_helper.py
pyshacl/inference/__init__.py
pyshacl/inference/custom_rdfs_closure.py
pyshacl/monkey/__init__.py
pyshacl/parameter.py
pyshacl/py.typed
pyshacl/pyshacl-cli.spec
pyshacl/pytypes.py
pyshacl/rdfutil/__init__.py
pyshacl/rdfutil/clone.py
pyshacl/rdfutil/compare.py
pyshacl/rdfutil/consts.py
pyshacl/rdfutil/inoculate.py
pyshacl/rdfutil/load.py
pyshacl/rdfutil/pytypes.py
pyshacl-0.30.0.dist-info/LICENSE.txt
pyshacl-0.30.0.dist-info/METADATA
pyshacl-0.30.0.dist-info/WHEEL
pyshacl-0.30.0.dist-info/entry_points.txt
pyshacl-0.30.0.dist-info/RECORD
