Metadata-Version: 2.3
Name: pyshacl
Version: 0.30.0
Summary: Python SHACL Validator
Home-page: https://github.com/RDFLib/pySHACL
License: Apache License
Keywords: Linked Data,Semantic Web,RDF,Graph,Python,SHACL,Shapes,Schema,Validate,Validator
Author: Ashley Sommer
Author-email: Ashley.Sommer@csiro.au
Requires-Python: >=3.9,<4
Classifier: License :: OSI Approved :: Apache Software License
Classifier: Development Status :: 5 - Production/Stable
Classifier: Topic :: Utilities
Classifier: Intended Audience :: Developers
Classifier: Natural Language :: English
Classifier: Programming Language :: Python :: Implementation :: CPython
Classifier: Programming Language :: Python :: Implementation :: PyPy
Classifier: Programming Language :: Python :: 3
Classifier: Programming Language :: Python :: 3 :: Only
Classifier: Programming Language :: Python :: 3.8
Classifier: Programming Language :: Python :: 3.9
Classifier: Programming Language :: Python :: 3.10
Classifier: Programming Language :: Python :: 3.11
Classifier: Programming Language :: Python :: 3.12
Classifier: Topic :: Software Development :: Libraries :: Python Modules
Classifier: Operating System :: OS Independent
Provides-Extra: dev-coverage
Provides-Extra: dev-lint
Provides-Extra: dev-type-checking
Provides-Extra: http
Provides-Extra: js
Requires-Dist: coverage (>6.1,!=6.1.1,<7) ; extra == "dev-coverage"
Requires-Dist: importlib-metadata (>6) ; python_version < "3.12"
Requires-Dist: mypy (>=1.13.0) ; extra == "dev-type-checking"
Requires-Dist: owlrl (>=7.1.2,<8)
Requires-Dist: packaging (>=21.3)
Requires-Dist: platformdirs ; extra == "dev-coverage"
Requires-Dist: platformdirs ; extra == "dev-lint"
Requires-Dist: platformdirs ; extra == "dev-type-checking"
Requires-Dist: prettytable (>=3.5.0) ; python_version < "3.12"
Requires-Dist: prettytable (>=3.7.0) ; python_version >= "3.12"
Requires-Dist: pyduktape2 (>=0.4.6,<1) ; extra == "js"
Requires-Dist: pytest-cov (>=2.8.1,<3) ; extra == "dev-coverage"
Requires-Dist: rdflib[html] (>=7.1.1,<8.0)
Requires-Dist: ruff (>=0.9.3,<0.10) ; extra == "dev-lint"
Requires-Dist: sanic (>=22.12,<23) ; extra == "http"
Requires-Dist: sanic-cors (==2.2.0) ; extra == "http"
Requires-Dist: sanic-ext (>=23.3,<23.6) ; extra == "http"
Requires-Dist: types-setuptools ; extra == "dev-type-checking"
Project-URL: changelog, https://github.com/RDFLib/pySHACL/blob/master/CHANGELOG.md
Project-URL: download, https://github.com/RDFLib/pySHACL/releases
Project-URL: issues, https://github.com/RDFLib/pySHACL/issues
Project-URL: source, https://github.com/RDFLib/pySHACL
